git_ai_reporter/__init__.py
git_ai_reporter/cli.py
git_ai_reporter/config.py
git_ai_reporter/models.py
git_ai_reporter/analysis/__init__.py
git_ai_reporter/analysis/git_analyzer.py
git_ai_reporter/cache/__init__.py
git_ai_reporter/cache/manager.py
git_ai_reporter/orchestration/__init__.py
git_ai_reporter/orchestration/orchestrator.py
git_ai_reporter/prompt_fitting/PROMPT_FITTING.md
git_ai_reporter/prompt_fitting/README.md
git_ai_reporter/prompt_fitting/__init__.py
git_ai_reporter/prompt_fitting/advanced_strategies.py
git_ai_reporter/prompt_fitting/analysis.py
git_ai_reporter/prompt_fitting/caching.py
git_ai_reporter/prompt_fitting/constants.py
git_ai_reporter/prompt_fitting/exceptions.py
git_ai_reporter/prompt_fitting/factory.py
git_ai_reporter/prompt_fitting/fallback.py
git_ai_reporter/prompt_fitting/logging.py
git_ai_reporter/prompt_fitting/parallel.py
git_ai_reporter/prompt_fitting/parameters.py
git_ai_reporter/prompt_fitting/plugins.py
git_ai_reporter/prompt_fitting/prompt_fitting.py
git_ai_reporter/prompt_fitting/validation.py
git_ai_reporter/prompt_fitting/monitoring/__init__.py
git_ai_reporter/prompt_fitting/monitoring/backends.py
git_ai_reporter/prompt_fitting/monitoring/models.py
git_ai_reporter/prompt_fitting/monitoring/monitor.py
git_ai_reporter/prompt_fitting/monitoring/rules.py
git_ai_reporter/prompt_fitting/utils/__init__.py
git_ai_reporter/prompt_fitting/utils/boundary_analysis.py
git_ai_reporter/prompt_fitting/utils/line_analysis.py
git_ai_reporter/prompt_fitting/utils/parallel_processing.py
git_ai_reporter/prompt_fitting/utils/semantic_analysis.py
git_ai_reporter/prompt_fitting/utils/strategy_selection.py
git_ai_reporter/services/__init__.py
git_ai_reporter/services/gemini.py
git_ai_reporter/summaries/SUMMARIES.md
git_ai_reporter/summaries/__init__.py
git_ai_reporter/summaries/commit.py
git_ai_reporter/summaries/daily.py
git_ai_reporter/summaries/weekly.py
git_ai_reporter/utils/UTILS_MODULE.md
git_ai_reporter/utils/__init__.py
git_ai_reporter-0.1.0.dist-info/METADATA
git_ai_reporter-0.1.0.dist-info/WHEEL
git_ai_reporter-0.1.0.dist-info/entry_points.txt
git_ai_reporter-0.1.0.dist-info/licenses/LICENSE
git_ai_reporter-0.1.0.dist-info/licenses/NOTICE
git_ai_reporter-0.1.0.dist-info/RECORD
