Metadata-Version: 2.4
Name: git-ai-reporter
Version: 0.1.0
Summary: AI-Driven Git Repository Analysis and Narrative Generation.
Project-URL: Homepage, https://github.com/paudley/git-ai-reporter
Project-URL: Repository, https://github.com/paudley/git-ai-reporter.git
Project-URL: Issues, https://github.com/paudley/git-ai-reporter/issues
Project-URL: Documentation, https://github.com/paudley/git-ai-reporter#readme
Author-email: "Blackcat Informatics® Inc." <paudley@blackcat.ca>
Maintainer-email: Patrick Audley <paudley@blackcat.ca>
License: MIT
License-File: LICENSE
License-File: NOTICE
Keywords: ai,changelog,documentation,gemini,git,release-notes
Classifier: Development Status :: 4 - Beta
Classifier: Intended Audience :: Developers
Classifier: License :: OSI Approved :: MIT License
Classifier: Operating System :: OS Independent
Classifier: Programming Language :: Python :: 3
Classifier: Programming Language :: Python :: 3.12
Classifier: Programming Language :: Python :: 3.13
Classifier: Topic :: Software Development :: Documentation
Classifier: Topic :: Software Development :: Version Control :: Git
Classifier: Topic :: Text Processing :: Linguistic
Classifier: Typing :: Typed
Requires-Python: >=3.12
Requires-Dist: aiofiles>=23.2.1
Requires-Dist: gitpython>=3.1.45
Requires-Dist: google-genai>=1.28.0
Requires-Dist: httpx>=0.27.0
Requires-Dist: json-repair>=0.14.0
Requires-Dist: pydantic-settings>=2.10.1
Requires-Dist: pydantic>=2.0.0
Requires-Dist: python-dotenv>=1.1.1
Requires-Dist: rich>=14.1.0
Requires-Dist: tenacity>=8.5.0
Requires-Dist: tolerantjson>=1.0.0
Requires-Dist: typer>=0.16.0
Requires-Dist: types-setuptools>=80.9.0.20250801
Provides-Extra: test
Requires-Dist: autopep8>=2.3.2; extra == 'test'
Requires-Dist: bandit>=1.8.6; extra == 'test'
Requires-Dist: bs4>=0.0.2; extra == 'test'
Requires-Dist: flake8>=7.3.0; extra == 'test'
Requires-Dist: hypothesis>=6.132.1; extra == 'test'
Requires-Dist: isort>=6.0.1; extra == 'test'
Requires-Dist: markdown>=3.8.2; extra == 'test'
Requires-Dist: mypy-extensions>=1.1.0; extra == 'test'
Requires-Dist: mypy>=1.17.1; extra == 'test'
Requires-Dist: pycodestyle>=2.14.0; extra == 'test'
Requires-Dist: pyflakes>=3.4.0; extra == 'test'
Requires-Dist: pylint-htmf>=0.1.1; extra == 'test'
Requires-Dist: pylint-plugin-utils>=0.9.0; extra == 'test'
Requires-Dist: pylint-pydantic>=0.3.5; extra == 'test'
Requires-Dist: pylint>=3.3.7; extra == 'test'
Requires-Dist: pytest-asyncio>=1.1.0; extra == 'test'
Requires-Dist: pytest-bdd>=7.4.0; extra == 'test'
Requires-Dist: pytest-check>=2.4.1; extra == 'test'
Requires-Dist: pytest-cov>=5.0.0; extra == 'test'
Requires-Dist: pytest-mypy>=0.10.4; extra == 'test'
Requires-Dist: pytest-pylint>=0.21.0; extra == 'test'
Requires-Dist: pytest-random-order>=1.1.2; extra == 'test'
Requires-Dist: pytest-recording>=0.13.1; extra == 'test'
Requires-Dist: pytest-snapshot>=0.9.0; extra == 'test'
Requires-Dist: pytest-sugar>=1.0.0; extra == 'test'
Requires-Dist: pytest-timeout>=2.3.2; extra == 'test'
Requires-Dist: pytest-xdist>=3.7.0; extra == 'test'
Requires-Dist: pytest>=8.4.1; extra == 'test'
Requires-Dist: types-aiofiles>=23.10.0.20240106; extra == 'test'
Requires-Dist: types-markdown>=3.8.0.20250708; extra == 'test'
Requires-Dist: types-python-dateutil>=2.9.0.20250708; extra == 'test'
Requires-Dist: types-pyyaml>=6.0.12.20250516; extra == 'test'
Requires-Dist: types-regex>=2024.11.6.20250403; extra == 'test'
Requires-Dist: typing-extensions>=4.14.1; extra == 'test'
Requires-Dist: typing-inspection>=0.4.1; extra == 'test'
Requires-Dist: uv>=0.8.4; extra == 'test'
Requires-Dist: vulture>=2.14; extra == 'test'
